<?xml version="1.0" encoding="UTF-8"?>
<strings locale="en_US" revision="6726">
  
  <string key="String ID 1">
   <original>XTM International a le plaisir d'annoncer Inter-language Vector Space, la technologie avancée basée sur un réseau de neurones qui jettera une base solide pour la stratégie XTM AI de XTM Cloud.</original>
  </string>  
  
  <string key="String ID 2">
   <original>Il s'agit sans doute de la plus grande avancée dans la technologie linguistique depuis la traduction automatique neuronale (NMT), une approche algorithmique mathématique unique pour l'avancement de la technologie linguistique basée sur des réseaux de neurones massifs.</original>
  </string>

</strings>